Workbook

Sheet Readme
A1: Read me first
A3: Sheets
A4: 1. Buildout — paste Amex/card lines → TOTAL shop build cost (start for buildout question) 2. YourMoney — how much of YOUR revenue paid rent/expenses 3. Summary — story + bottom-line numbers 4. Assumptions — 75/25 ownership, $45k/$15k, rent/ops 5. Scenarios / MonthlyTracker / TrueUp / CapitalAccounts
A6: Two different questions
A7: A) BUILDOUT COST (one-time): what did it cost to open the shop? → Buildout sheet + Amex/CSVs. B) MONTHLY BURN / REVENUE: what did operations cost after open? → YourMoney / MonthlyTracker. Ownership = 75/25 ($45k / $15k). At break-even ballpark, ~$11,250 of Cesar's revenue share paid bills. Do not mix rent/utilities into Buildout — mark those Buildout?=No.

Sheet Buildout
A1: Shop buildout from Amex (imported)
A2: Amex + manual contractor. Total buildout ~$45,178. $11,600 Alexis contractor is SPLIT 50/50 (Cesar $5,800 / Partner $5,800). If Cesar fronted all of it, Partner owes Cesar $5,800.
A4: TOTALS | D4: BY CATEGORY (Yes)
A5: Metric | B5: Amount | D5: Category | E5: Amount
A6: BUILDOUT confident (Amex Yes + $11,600 contractor) | B6: 45178.03 | D6: Flooring / paint / finishes | E6: 11845.69
A7: BUILDOUT + Review | B7: 45305.39 | D7: Waiting area / furniture | E7: 6299.73
A8: Ops / utilities / fees | B8: 1267.06 | D8: Construction / contractor / permits | E8: 4350
A9: Personal excluded | B9: 1177.09 | D9: Other buildout | E9: 3644.16
D10: Plumbing / electrical / HVAC | E10: 2609.06
D11: Opening supplies / inventory | E11: 2294.67
A12: STATEMENT LINES (Yes + Review only) | D12: POS / computers / cameras / WiFi | E12: 1499.39
A13: Date | B13: Card member | C13: Description | D13: Amount | E13: Category | F13: Buildout? | G13: Paid by | H13: Notes
A14: 01/22/2026 | B14: CESAR SILVA | C14: PAYPAL *IRONCLIDLOG 13291871846 HK | D14: 88.36 | E14: Other buildout | F14: Review | G14: Cesar | H14: PayPal Ironclid — confirm
A15: 01/23/2026 | B15: CESAR SILVA | C15: GRANITE EXPO OUTLET 510-813-9451 CA | D15: 54.63 | E15: Flooring / paint / finishes | F15: Yes | G15: Cesar | H15: Granite Expo
A16: 01/23/2026 | B16: CESAR SILVA | C16: GRANITE EXPO OUTLET 510-813-9451 CA | D16: 819.38 | E16: Flooring / paint / finishes | F16: Yes | G16: Cesar | H16: Granite Expo
A17: 01/23/2026 | B17: CESAR SILVA | C17: GRANITE EXPO OUTLET 510-813-9451 CA | D17: 3061.28 | E17: Flooring / paint / finishes | F17: Yes | G17: Cesar | H17: Granite Expo
A18: 01/23/2026 | B18: CESAR SILVA | C18: OMNIHOMEINC 8885579288 NJ | D18: 5489.85 | E18: Waiting area / furniture | F18: Yes | G18: Cesar | H18: Omnihome — furniture/fixtures (confirm)
A19: 01/23/2026 | B19: CESAR SILVA | C19: THE HOME DEPOT PITTSBURG CA | D19: 174.73 | E19: Flooring / paint / finishes | F19: Yes | G19: Cesar | H19: Home Depot
A20: 01/24/2026 | B20: CESAR SILVA | C20: GRANITE EXPO STOCKTON CA | D20: 1169.97 | E20: Flooring / paint / finishes | F20: Yes | G20: Cesar | H20: Granite Expo
A21: 01/25/2026 | B21: CESAR SILVA | C21: THE HOME DEPOT PITTSBURG CA | D21: -174.73 | E21: Flooring / paint / finishes | F21: Yes | G21: Cesar | H21: Home Depot
A22: 01/25/2026 | B22: CESAR SILVA | C22: THE HOME DEPOT 644 PITTSBURG CA | D22: 791.8 | E22: Flooring / paint / finishes | F22: Yes | G22: Cesar | H22: Home Depot
A23: 01/27/2026 | B23: CESAR SILVA | C23: AplPay THE HOME DEPOPITTSBURG CA | D23: 529.16 | E23: Flooring / paint / finishes | F23: Yes | G23: Cesar | H23: Home Depot
A24: 01/28/2026 | B24: CESAR SILVA | C24: BEST BUY 010462ANTIOCH CA | D24: 174.48 | E24: POS / computers / cameras / WiFi | F24: Yes | G24: Cesar | H24: Electronics / POS
A25: 01/28/2026 | B25: CESAR SILVA | C25: BEST BUY 010462ANTIOCH CA | D25: 305.8 | E25: POS / computers / cameras / WiFi | F25: Yes | G25: Cesar | H25: Electronics / POS
... A98: 2026-02/03 | B98: Alexis (cash/transfer) | C98: Cash/transfer so Alexis can pay contractor | D98: 11600 | E98: Construction / contractor / permits | F98: Yes | G98: Split 50/50 | H98: Full $11,600 is buildout; economic split Cesar $5,800 / Partner $5,800

Sheet YourMoney
A1: How much of YOUR revenue paid rent & expenses?
A2: Rule: ownership = capital = 75% Cesar / 25% Omi. Bills come out of the shop account first. Your revenue toward rent = your 75% share of the revenue that covered bills.
A4: INPUTS (yellow = edit)
A5: Input | B5: Amount | C5: Notes
A6: Monthly rent | B6: =Assumptions!B21 | C6: $1,700
A7: Other monthly expenses | B7: =Assumptions!B22 | C7: ~$800
A8: Months paying from account | B8: =Assumptions!B25 | C8: ~6
A9: Total shop revenue (all months) | B9: 15000 | C9: Default $15,000 = break-even (= burn). Replace with real deposits if different.
A10: Optional: YOUR personal chair $ deposited | B10: 0 | C10: Leave 0 to use 75% of shop revenue. Fill only if you track your cuts separately.
A12: RESULTS — revenue that paid the bills
A13: What | B13: Amount | C13: Meaning
A14: Total rent + expenses (burn) | B14: =(B6+B7)*B8 | C14: What left the shop account for bills
A15: Shop revenue used to cover bills | B15: =MIN(B9,B14) | C15: Revenue applied to bills (capped at burn)
A16: YOUR revenue that paid rent/expenses (75%) | B16: =B15*Assumptions!B5 | C16: THE NUMBER — your ownership share of revenue that covered bills
A17: OMI's revenue that paid rent/expenses (25%) | B17: =B15*Assumptions!C5 | C17: His ownership share of revenue that covered bills
A18: Leftover after bills (shop-level) | B18: =B9-B14 | C18: ~$0 at break-even = no draw
A19: Your possible draw (75% of leftover) | B19: =MAX(0,B18)*Assumptions!B5 | C19: Why it feels like $0 take-home right now
A20: Chair-deposit version (only if B10 > 0) | B20: =IF(B10>0,MIN(B10,B14*Assumptions!B5),B16) | C20: Optional alternate if you track personal cuts
A22: Monthly going forward (75/25)
A23: Monthly burn | B23: =B6+B7
A24: You cover (75%) | B24: =B23*Assumptions!B5
A25: Omi covers (25%) | B25: =B23*Assumptions!C5
A27: How to read this
A28: At break-even, shop revenue ≈ rent+expenses. No leftover to take home. Your 75% ownership means ~75% of that revenue was your economic share — and it paid bills. On the $15k / 6-month ballpark: about $11,250 of YOUR revenue went to rent & expenses. Omi's 25% ≈ $3,750. Going forward he should fund ~$625/mo (25% of $2,500).

Sheet Summary
A1: The Barber Lounge — Partnership Economics
A2: Ownership locked to capital: Cesar 75% / Omi 25% ($45k / $15k). YourMoney shows how much of YOUR revenue share paid rent and expenses.
A4: HOW TO USE
A5: Yellow cells are editable inputs. Green cells are calculated. Update Assumptions, then fill Monthly Tracker with real months. True-Up shows what Partner owes Cesar under a fair ownership split.
A7: OWNERSHIP SNAPSHOT
B8: Cesar (You) | C8: Partner | D8: Total / Note
A9: Ownership % | B9: =Assumptions!B5 | C9: =Assumptions!C5 | D9: Must equal 100%
A10: Startup capital put in | B10: =Assumptions!B6 | C10: =Assumptions!C6 | D10: =Assumptions!D6
A11: % of capital funded | B11: =Assumptions!B7 | C11: =Assumptions!C7 | D11: Should match ownership
A12: Share of expenses they SHOULD pay | B12: =Assumptions!B5 | C12: =Assumptions!C5 | D12: By ownership
A13: Share of expenses they ACTUALLY fund (current) | B13: =Assumptions!B12 | C13: =Assumptions!C12 | D13: Current practice
A15: THE PROBLEM (plain English)
A16: 1) Capital + ownership: Cesar $45,000 (75%) / Omi $15,000 (25%) = $60,000. 2) Rent + expenses come out of the shop bank account first (recently always). 3) Profit draws (when leftover exists) follow 75/25. 4) At break-even, leftover = $0 so draws = $0 — but revenue still paid the bills. 5) 'How much of my revenue went to rent/expenses?' = your 75% ownership share of whatever revenue was used to cover bills (at break-even ≈ 75% of total expenses). 6) Omi should fund 25% of the monthly burn going forward (~$625/mo at current rent/ops).
A18: BOTTOM-LINE NUMBERS (from Monthly Tracker)
A19: Metric | B19: Amount | C19: Meaning
A20: Total revenue logged | B20: =MonthlyTracker!B37 | C20: All months entered
A21: Total expenses logged (rent + ops) | B21: =MonthlyTracker!B38 | C21: Paid from joint account
A22: Total leftover / 'profit' logged | B22: =MonthlyTracker!B39 | C22: After expenses
A23: Cesar capital in (startup) | B23: =Assumptions!B6 | C23: Your $45k
A24: Omi capital in (startup) | B24: =Assumptions!C6 | C24: His $15k
A25: Expense true-up Omi → Cesar | B25: =TrueUp!B12 | C25: If he underfunded his 25%
A26: Extra profit Omi took vs 25% | B26: =TrueUp!B18 | C26: If past draws exceeded ownership
A27: TOTAL Omi owes Cesar (suggested) | B27: =TrueUp!B20 | C27: True-up total
A28: YOUR revenue that paid rent/ops | B28: =YourMoney!B16 | C28: 75% of revenue applied to bills
A30: RECOMMENDATION (for the conversation)
A31: Ownership = capital = 75/25. Expenses and profit draws follow that. Going forward: Omi transfers 25% of rent+ops into the shop account each month (~$625 at $2,500 burn). Cesar covers 75% (~$1,875). If the account is already funded by revenue, you are not 'paying half' — you are applying 75% of shop revenue to bills. Track that on YourMoney. Only go 50/50 on expenses if ownership becomes 50/50 via buy-up.
A33: Legend: | B33: Editable input | C33: Calculated | D33: Money Partner likely owes / your revenue to bills

Sheet Assumptions
A1: Assumptions (edit yellow cells)
A3: OWNERSHIP & STARTUP CAPITAL
B4: Cesar | C4: Partner | D4: Total
A5: Ownership % | B5: 0.75 | C5: 0.25 | D5: =B5+C5 | E5: Partner $ claimed | F5: Partner $ documented | G5: Audit file
A6: Startup capital contributed ($) | B6: 45000 | C6: 15000 | D6: =B6+C6 | E6: 16000 | F6: 0 | G6: finance/partner-money-received.xlsx
A7: % of capital funded | B7: =IF(D6=0,0,B6/D6) | C7: =IF(D6=0,0,C6/D6) | D7: 1
A9: CURRENT (BROKEN) PRACTICE
A10: Expenses paid from joint account in proportion to who funded the account (default = ownership). Profit leftover was split at the rates below (default 50/50).
B11: Cesar | C11: Partner | D11: Total
A12: Who actually funds expenses today | B12: 0.75 | C12: 0.25 | D12: =B12+C12
A13: How leftover profit was split | B13: 0.75 | C13: 0.25 | D13: =B13+C13
A15: FAIR RULE (target)
B16: Cesar | C16: Partner | D16: Total
A17: Fair expense split (= ownership) | B17: =B5 | C17: =C5 | D17: =B17+C17
A18: Fair profit split (= ownership) | B18: =B5 | C18: =C5 | D18: =B18+C18
A20: OPTIONAL: monthly rent / baseline ops (for Scenario examples)
A21: Example monthly rent | B21: 1700
A22: Example other monthly expenses | B22: 800
A23: Example monthly revenue (break-even case) | B23: 2500
A24: Example monthly revenue (profit case) | B24: 5000
A25: Months open (for quick estimate) | B25: 6
A27: Notes
A28: • Ownership = capital = Cesar 75% / Omi 25% ($45k / $15k of $60k). • Expense funding and profit draws both follow 75/25. • YourMoney answers: how much of Cesar's revenue share paid rent/expenses. • This workbook is a negotiation tool, not legal advice. Put the final deal in writing.
A30: Partner capital-in is UNDER AUDIT
A31: Do not trust verbal $16k/$19k. Use finance/partner-money-received.xlsx Transfers ledger. Fair 25% of ~$58,841 shop list ≈ $14,710. Prior model cell used $15,000 as placeholder.

Sheet Scenarios
A1: Side-by-side: one month under current vs fair rules
A3: BREAK-EVEN MONTH (uses Assumptions example revenue/expenses)
B4: Current practice | C4: Fair 80/20 | D4: Difference (Fair − Current for Cesar) | F4: Break-even net
A5: Revenue | B5: =Assumptions!B23 | C5: =Assumptions!B23 | D5: =C5-B5 | F5: Cesar current | G5: =B12
A6: Rent + expenses | B6: =Assumptions!B21+Assumptions!B22 | C6: =Assumptions!B21+Assumptions!B22 | D6: =C6-B6 | F6: Partner current | G6: =B13
A7: Leftover after expenses | B7: =B5-B6 | C7: =C5-C6 | D7: =C7-B7 | F7: Cesar fair | G7: =C12
A8: Cesar's share of leftover | B8: =IF(B7>0,B7*Assumptions!B13,0) | C8: =IF(C7>0,C7*Assumptions!B18,0) | D8: =C8-B8 | F8: Partner fair | G8: =C13
A9: Partner's share of leftover | B9: =IF(B7>0,B7*Assumptions!C13,0) | C9: =IF(C7>0,C7*Assumptions!C18,0) | D9: =C9-B9
A10: Cesar economic cost of expenses (funded share) | B10: =B6*Assumptions!B12 | C10: =C6*Assumptions!B17 | D10: =C10-B10
A11: Partner economic cost of expenses (funded share) | B11: =B6*Assumptions!C12 | C11: =C6*Assumptions!C17 | D11: =C11-B11
A12: Cesar net this month (leftover share − expense cost) | B12: =B8-B10 | C12: =C8-C10 | D12: =C12-B12
A13: Partner net this month | B13: =B9-B11 | C13: =C9-C11 | D13: =C13-B13
A15: PROFIT MONTH
B16: Current practice | C16: Fair 80/20 | D16: Difference (Fair − Current for Cesar)
A17: Revenue | B17: =Assumptions!B24 | C17: =Assumptions!B24 | D17: =C17-B17
A18: Rent + expenses | B18: =Assumptions!B21+Assumptions!B22 | C18: =Assumptions!B21+Assumptions!B22 | D18: =C18-B18
A19: Leftover after expenses | B19: =B17-B18 | C19: =C17-C18 | D19: =C19-B19
A20: Cesar's share of leftover | B20: =IF(B19>0,B19*Assumptions!B13,0) | C20: =IF(C19>0,C19*Assumptions!B18,0) | D20: =C20-B20
A21: Partner's share of leftover | B21: =IF(B19>0,B19*Assumptions!C13,0) | C21: =IF(C19>0,C19*Assumptions!C18,0) | D21: =C21-B21
A22: Cesar economic cost of expenses | B22: =B18*Assumptions!B12 | C22: =C18*Assumptions!B17 | D22: =C22-B22
A23: Partner economic cost of expenses | B23: =B18*Assumptions!C12 | C23: =C18*Assumptions!C17 | D23: =C23-B23
A24: Cesar net this month | B24: =B20-B22 | C24: =C20-C22 | D24: =C24-B24
A25: Partner net this month | B25: =B21-B23 | C25: =C21-C23 | D25: =C25-B25
A27: Buy-up to 50/50 (if Partner wants equal splits)
A28: Total startup capital | B28: =Assumptions!D6
A29: 50% of capital | B29: =B28*0.5
A30: Partner already put in | B30: =Assumptions!C6
A31: Cash Partner must add to reach 50% | B31: =MAX(0,B29-B30)
A32: If they pay that buy-up (and agree expenses + profits go 50/50 from then on), equal splits are fair. Until then, 50/50 profit while you carry 80% of capital is the imbalance.

Sheet MonthlyTracker
A1: Monthly Tracker — enter real numbers (yellow)
A2: For each month: revenue, rent, other expenses, any profit already paid out, and any personal cash each partner put in that month. Leave unused months blank (or zero).
A4: Month | B4: Revenue | C4: Rent | D4: Other expenses | E4: Total expenses | F4: Leftover | G4: Profit paid to Cesar | H4: Profit paid to Partner | I4: Cesar personal cash in | J4: Partner personal cash in | K4: Cesar should fund (80%) | L4: Partner should fund (20%) | M4: Cesar overfunded expenses | N4: Partner profit overpay vs 20%
A5: 2025-03 | B5: 2500 | C5: 1700 | D5: 800 | E5: =C5+D5 | F5: =B5-E5 | G5: 0 | H5: 0 | I5: 0 | J5: 0 | K5: =E5*Assumptions!$B$17-I5 | L5: =E5*Assumptions!$C$17-J5 | M5: =MAX(0,L5) | N5: =H5-MAX(0,F5)*Assumptions!$C$18
A6: 2025-04 | B6: 2500 | C6: 1700 | D6: 800 | E6: =C6+D6 | F6: =B6-E6 | G6: 0 | H6: 0 | I6: 0 | J6: 0 | K6: =E6*Assumptions!$B$17-I6 | L6: =E6*Assumptions!$C$17-J6 | M6: =MAX(0,L6) | N6: =H6-MAX(0,F6)*Assumptions!$C$18
A7: 2025-05 | B7: 2500 | C7: 1700 | D7: 800 | E7: =C7+D7 | F7: =B7-E7 | G7: 0 | H7: 0 | I7: 0 | J7: 0 | K7: =E7*Assumptions!$B$17-I7 | L7: =E7*Assumptions!$C$17-J7 | M7: =MAX(0,L7) | N7: =H7-MAX(0,F7)*Assumptions!$C$18
A8: 2025-06 | B8: 2500 | C8: 1700 | D8: 800 | E8: =C8+D8 | F8: =B8-E8 | G8: 0 | H8: 0 | I8: 0 | J8: 0 | K8: =E8*Assumptions!$B$17-I8 | L8: =E8*Assumptions!$C$17-J8 | M8: =MAX(0,L8) | N8: =H8-MAX(0,F8)*Assumptions!$C$18
A9: 2025-07 | B9: 2500 | C9: 1700 | D9: 800 | E9: =C9+D9 | F9: =B9-E9 | G9: 0 | H9: 0 | I9: 0 | J9: 0 | K9: =E9*Assumptions!$B$17-I9 | L9: =E9*Assumptions!$C$17-J9 | M9: =MAX(0,L9) | N9: =H9-MAX(0,F9)*Assumptions!$C$18
A10: 2025-08 | B10: 2500 | C10: 1700 | D10: 800 | E10: =C10+D10 | F10: =B10-E10 | G10: 0 | H10: 0 | I10: 0 | J10: 0 | K10: =E10*Assumptions!$B$17-I10 | L10: =E10*Assumptions!$C$17-J10 | M10: =MAX(0,L10) | N10: =H10-MAX(0,F10)*Assumptions!$C$18
B11: 0 | C11: 0 | D11: 0 | E11: =C11+D11 | F11: =B11-E11 | G11: 0 | H11: 0 | I11: 0 | J11: 0 | K11: =E11*Assumptions!$B$17-I11 | L11: =E11*Assumptions!$C$17-J11 | M11: =MAX(0,L11) | N11: =H11-MAX(0,F11)*Assumptions!$C$18
B12: 0 | C12: 0 | D12: 0 | E12: =C12+D12 | F12: =B12-E12 | G12: 0 | H12: 0 | I12: 0 | J12: 0 | K12: =E12*Assumptions!$B$17-I12 | L12: =E12*Assumptions!$C$17-J12 | M12: =MAX(0,L12) | N12: =H12-MAX(0,F12)*Assumptions!$C$18
B13: 0 | C13: 0 | D13: 0 | E13: =C13+D13 | F13: =B13-E13 | G13: 0 | H13: 0 | I13: 0 | J13: 0 | K13: =E13*Assumptions!$B$17-I13 | L13: =E13*Assumptions!$C$17-J13 | M13: =MAX(0,L13) | N13: =H13-MAX(0,F13)*Assumptions!$C$18
B14: 0 | C14: 0 | D14: 0 | E14: =C14+D14 | F14: =B14-E14 | G14: 0 | H14: 0 | I14: 0 | J14: 0 | K14: =E14*Assumptions!$B$17-I14 | L14: =E14*Assumptions!$C$17-J14 | M14: =MAX(0,L14) | N14: =H14-MAX(0,F14)*Assumptions!$C$18
B15: 0 | C15: 0 | D15: 0 | E15: =C15+D15 | F15: =B15-E15 | G15: 0 | H15: 0 | I15: 0 | J15: 0 | K15: =E15*Assumptions!$B$17-I15 | L15: =E15*Assumptions!$C$17-J15 | M15: =MAX(0,L15) | N15: =H15-MAX(0,F15)*Assumptions!$C$18
B16: 0 | C16: 0 | D16: 0 | E16: =C16+D16 | F16: =B16-E16 | G16: 0 | H16: 0 | I16: 0 | J16: 0 | K16: =E16*Assumptions!$B$17-I16 | L16: =E16*Assumptions!$C$17-J16 | M16: =MAX(0,L16) | N16: =H16-MAX(0,F16)*Assumptions!$C$18
B17: 0 | C17: 0 | D17: 0 | E17: =C17+D17 | F17: =B17-E17 | G17: 0 | H17: 0 | I17: 0 | J17: 0 | K17: =E17*Assumptions!$B$17-I17 | L17: =E17*Assumptions!$C$17-J17 | M17: =MAX(0,L17) | N17: =H17-MAX(0,F17)*Assumptions!$C$18
B18: 0 | C18: 0 | D18: 0 | E18: =C18+D18 | F18: =B18-E18 | G18: 0 | H18: 0 | I18: 0 | J18: 0 | K18: =E18*Assumptions!$B$17-I18 | L18: =E18*Assumptions!$C$17-J18 | M18: =MAX(0,L18) | N18: =H18-MAX(0,F18)*Assumptions!$C$18
B19: 0 | C19: 0 | D19: 0 | E19: =C19+D19 | F19: =B19-E19 | G19: 0 | H19: 0 | I19: 0 | J19: 0 | K19: =E19*Assumptions!$B$17-I19 | L19: =E19*Assumptions!$C$17-J19 | M19: =MAX(0,L19) | N19: =H19-MAX(0,F19)*Assumptions!$C$18
B20: 0 | C20: 0 | D20: 0 | E20: =C20+D20 | F20: =B20-E20 | G20: 0 | H20: 0 | I20: 0 | J20: 0 | K20: =E20*Assumptions!$B$17-I20 | L20: =E20*Assumptions!$C$17-J20 | M20: =MAX(0,L20) | N20: =H20-MAX(0,F20)*Assumptions!$C$18
B21: 0 | C21: 0 | D21: 0 | E21: =C21+D21 | F21: =B21-E21 | G21: 0 | H21: 0 | I21: 0 | J21: 0 | K21: =E21*Assumptions!$B$17-I21 | L21: =E21*Assumptions!$C$17-J21 | M21: =MAX(0,L21) | N21: =H21-MAX(0,F21)*Assumptions!$C$18
B22: 0 | C22: 0 | D22: 0 | E22: =C22+D22 | F22: =B22-E22 | G22: 0 | H22: 0 | I22: 0 | J22: 0 | K22: =E22*Assumptions!$B$17-I22 | L22: =E22*Assumptions!$C$17-J22 | M22: =MAX(0,L22) | N22: =H22-MAX(0,F22)*Assumptions!$C$18
... B33: 0 | C33: 0 | D33: 0 | E33: =C33+D33 | F33: =B33-E33 | G33: 0 | H33: 0 | I33: 0 | J33: 0 | K33: =E33*Assumptions!$B$17-I33 | L33: =E33*Assumptions!$C$17-J33 | M33: =MAX(0,L33) | N33: =H33-MAX(0,F33)*Assumptions!$C$18
A34: TOTALS | B34: =SUM(B5:B33) | C34: =SUM(C5:C33) | D34: =SUM(D5:D33) | E34: =SUM(E5:E33) | F34: =SUM(F5:F33) | G34: =SUM(G5:G33) | H34: =SUM(H5:H33) | I34: =SUM(I5:I33) | ... N34: =SUM(N5:N33)
A36: Summary hooks (do not edit)
A37: Total revenue | B37: =B34
A38: Total expenses | B38: =E34
A39: Total leftover | B39: =F34
A41: Uses Cesar's ballpark: $1,700 rent + ~$800 other × 6 months, break-even revenue. Overwrite with bank/statement totals when you have them.

Sheet TrueUp
A1: True-Up — what Partner should pay Cesar
A3: 1) EXPENSE TRUE-UP
A4: Partner's fair share of all logged expenses (by ownership), minus what they already paid from personal cash. That shortfall was effectively covered by your capital in the joint account.
A6: Item | B6: Amount
A7: Total expenses (all months) | B7: =MonthlyTracker!E34
A8: Partner fair share of expenses | B8: =MonthlyTracker!E34*Assumptions!C17
A9: Partner personal cash already paid in | B9: =MonthlyTracker!J34
A10: Partner still owes for expenses | B10: =MAX(0,B8-B9)
A11: Cesar fair share of expenses | B11: =MonthlyTracker!E34*Assumptions!B17
A12: Expense true-up Partner → Cesar | B12: =B10
A14: 2) PROFIT CATCH-UP (if past leftovers were split 50/50)
A15: If Partner was paid 50% of leftovers while only owning 20%, they were overpaid relative to ownership. Set to $0 on Assumptions if you already agreed profits were intentionally 50/50 as sweat equity — then only use the expense true-up.
A17: Item | B17: Amount
A18: Partner profit overpay vs 20% ownership (sum) | B18: =MAX(0,MonthlyTracker!N34)
A19: Include profit catch-up in total? (1=yes, 0=no) | B19: 1
A20: TOTAL suggested true-up Partner pays Cesar | B20: =B12+B19*B18
A22: 3) GOING FORWARD — pick a written rule
A23: Option A — Stay 80/20: every month, Partner transfers 20% of rent+ops to the joint account (or you invoice them). Profit distributions also 80/20. Option B — Buy up to 50/50: Partner pays the capital buy-up on Scenarios!B31, then expenses and profits split 50/50. Option C — Loan: record Cesar's excess capital as a loan; no profit distributions to Partner until loan is current. Until one of these is written down, keep logging months in Monthly Tracker so the true-up number stays current.
A25: Simple talk track
A26: "Ownership is 75/25 — same as the $45k / $15k we put in. Bills come out of the shop account first. At break-even my revenue share still paid about 75% of rent and expenses, and there's nothing left to draw. Going forward you put in 25% of the monthly burn (~$625) so the account isn't only my money."
A28: NEW DEAL (Cesar sit-down)
A29: Sit at $60k → $30k each. Document partner sends (no verbal $16k/$19k). Until documented = $30k: expenses 50/50 from PERSONAL pockets (not shop account). Historical clawback = his 50% of bills paid from shop account (ballpark $7,500 on 6×$2,500). See finance/cesar-money-clawback.xlsx.

Sheet CapitalAccounts
A1: Capital Accounts (running picture)
A2: Starting capital → minus fair share of expenses → plus profit allocations → plus personal cash. If Partner's balance goes negative vs fair contributions, that's the debt.
B4: Cesar | C4: Partner | D4: Combined
A5: Starting capital | B5: =Assumptions!B6 | C5: =Assumptions!C6 | D5: =B5+C5
A6: + Personal cash contributed (tracker) | B6: =MonthlyTracker!I34 | C6: =MonthlyTracker!J34 | D6: =B6+C6
A7: − Fair share of expenses | B7: =MonthlyTracker!E34*Assumptions!B17 | C7: =MonthlyTracker!E34*Assumptions!C17 | D7: =B7+C7
A8: + Fair share of positive leftovers | B8: =MAX(0,MonthlyTracker!F34)*Assumptions!B18 | C8: =MAX(0,MonthlyTracker!F34)*Assumptions!C18 | D8: =B8+C8
A9: − Profit already distributed | B9: =MonthlyTracker!G34 | C9: =MonthlyTracker!H34 | D9: =B9+C9
A10: Ending capital (model) | B10: =B5+B6-B7+B8-B9 | C10: =C5+C6-C7+C8-C9 | D10: =B10+C10
A12: Partner capital gap vs 20% of combined ending capital
A13: Partner should hold (ownership × combined) | B13: =D10*Assumptions!C5
A14: Partner actually holds (model) | B14: =C10
A15: Gap (positive = Partner under-capitalized / owes value) | B15: =B13-B14

Sheet _Lists
A1: Lease deposit / first-last
A2: Construction / contractor / permits
A3: Plumbing / electrical / HVAC
A4: Flooring / paint / finishes
A5: Barber chairs / stations / mirrors
A6: Waiting area / furniture
A7: Signage / exterior / branding
A8: POS / computers / cameras / WiFi
A9: Opening supplies / inventory
A10: Licenses / legal / LLC / insurance setup
A11: Marketing / grand opening
A12: Other buildout
